{
    "type": "application",
    "source-directories": [
        "src"
    ],
    "elm-version": "0.19.0",
    "source-directories": [
        "./src/MathEquation/Elm",
        "./src/MathEquation/Stylesheets"
    ],
    "dependencies": {
        "direct": {
		"elm-lang/core": "5.1.1",
		"elm-lang/html": "2.0.0",
		"elm-lang/mouse": "1.0.1",
		"elm-lang/window": "1.0.1",
		"rtfeldman/elm-css": "11.2.0",
		"rtfeldman/elm-css-helpers": "2.1.0"
        },
        "indirect": {
            "elm/json": "1.0.0",
            "elm/time": "1.0.0",
            "elm/url": "1.0.0",
            "elm/virtual-dom": "1.0.2"
        }
    },
    "test-dependencies": {
        "direct": {},
        "indirect": {}
    }
}
